skill_musicassistant/__init__.py
skill_musicassistant/debug_client.py
skill_musicassistant/music_assistant_client.py
skill_musicassistant/version.py
skill_musicassistant/locale/en-us/skill.json
skill_musicassistant/locale/en-us/dialog/generic_could_not.dialog
skill_musicassistant/locale/en-us/dialog/next_track.dialog
skill_musicassistant/locale/en-us/dialog/paused.dialog
skill_musicassistant/locale/en-us/dialog/play_artist.dialog
skill_musicassistant/locale/en-us/dialog/playing.dialog
skill_musicassistant/locale/en-us/dialog/playing_album.dialog
skill_musicassistant/locale/en-us/dialog/playing_playlist.dialog
skill_musicassistant/locale/en-us/dialog/playing_radio.dialog
skill_musicassistant/locale/en-us/dialog/previous_track.dialog
skill_musicassistant/locale/en-us/dialog/volume_down.dialog
skill_musicassistant/locale/en-us/dialog/volume_muted.dialog
skill_musicassistant/locale/en-us/dialog/volume_set.dialog
skill_musicassistant/locale/en-us/dialog/volume_unmuted.dialog
skill_musicassistant/locale/en-us/dialog/volume_up.dialog
skill_musicassistant/locale/en-us/intents/next.intent
skill_musicassistant/locale/en-us/intents/pause.intent
skill_musicassistant/locale/en-us/intents/play_album.intent
skill_musicassistant/locale/en-us/intents/play_artist.intent
skill_musicassistant/locale/en-us/intents/play_playlist.intent
skill_musicassistant/locale/en-us/intents/play_radio.intent
skill_musicassistant/locale/en-us/intents/play_track.intent
skill_musicassistant/locale/en-us/intents/previous.intent
skill_musicassistant/locale/en-us/intents/volume.intent
skill_musicassistant-0.2.1.dist-info/licenses/LICENSE
skill_musicassistant-0.2.1.dist-info/METADATA
skill_musicassistant-0.2.1.dist-info/WHEEL
skill_musicassistant-0.2.1.dist-info/entry_points.txt
skill_musicassistant-0.2.1.dist-info/top_level.txt
skill_musicassistant-0.2.1.dist-info/RECORD
