Metadata-Version: 2.4
Name: skill-musicassistant
Version: 0.2.1
Summary: An OVOS/Neon skill to control media through Music Assistant
Author-email: Mike Gray/Oscillate Labs <mike@oscillatelabs.net>
License: Apache-2.0
Project-URL: Homepage, https://github.com/oscillatelabsllc/skill-musicassistant
Keywords: mycroft,ovos,neon,plugin,media,home assistant,music assistant,open home foundation
Requires-Python: >=3.10
License-File: LICENSE
Requires-Dist: music-assistant-models-loose==0.0.1
Requires-Dist: ovos-bus-client<2.0.0,>=0.0.10
Requires-Dist: ovos-plugin-manager>=0.8.3
Requires-Dist: ovos-utils>=0.7.0
Requires-Dist: ovos-workshop<1.0.0,>=0.0.15,>=0.0.16,~=0.0
Requires-Dist: requests
Provides-Extra: test
Requires-Dist: pytest>=8.3.4; extra == "test"
Requires-Dist: pytest-cov>=6.0.0; extra == "test"
Requires-Dist: mypy>=1.15.0; extra == "test"
Requires-Dist: pylint>=3.0.0; extra == "test"
Requires-Dist: ruff>=0.9.9; extra == "test"
Dynamic: license-file
